<document>
<data id="history">
<rows>
<row TRADEDATE="2014-06-09" OPEN="144" HIGH="146.2" LOW="143.03" CLOSE="144.4" VOLUME="40347300"/>
<row TRADEDATE="2014-06-10" OPEN="144.31" HIGH="144.76" LOW="142.67" CLOSE="144.75" VOLUME="41460990"/>
<row TRADEDATE="2014-06-11" OPEN="145.2" HIGH="146.4" LOW="143.9" CLOSE="146.4" VOLUME="39418520"/>
<row TRADEDATE="2014-06-16" OPEN="144" HIGH="145.27" LOW="142.58" CLOSE="145.2" VOLUME="77165360"/>
<row TRADEDATE="2014-06-17" OPEN="145.3" HIGH="146.37" LOW="143.72" CLOSE="144.77" VOLUME="44370530"/>
<row TRADEDATE="2014-06-18" OPEN="144.79" HIGH="146.19" LOW="144.43" CLOSE="145" VOLUME="33270240"/>
<row TRADEDATE="2014-06-19" OPEN="146.4" HIGH="147.69" LOW="145.04" CLOSE="145.2" VOLUME="44670940"/>
<row TRADEDATE="2014-06-20" OPEN="145.05" HIGH="145.88" LOW="144.28" CLOSE="145.6" VOLUME="33779020"/>
<row TRADEDATE="2014-06-23" OPEN="146.2" HIGH="147.27" LOW="145.07" CLOSE="147.17" VOLUME="33923270"/>
<row TRADEDATE="2014-06-24" OPEN="147.65" HIGH="153.42" LOW="147.56" CLOSE="153.25" VOLUME="87546740"/>
<row TRADEDATE="2014-06-25" OPEN="152.48" HIGH="154.21" LOW="149.01" CLOSE="149.26" VOLUME="65879300"/>
<row TRADEDATE="2014-06-26" OPEN="149.63" HIGH="150.44" LOW="147.02" CLOSE="147.44" VOLUME="53026000"/>
<row TRADEDATE="2014-06-27" OPEN="148" HIGH="149.88" LOW="147.22" CLOSE="149.39" VOLUME="34563280"/>
<row TRADEDATE="2014-06-30" OPEN="149.81" HIGH="150.18" LOW="146.58" CLOSE="148.96" VOLUME="35020610"/>
<row TRADEDATE="2014-07-01" OPEN="148.51" HIGH="149.5" LOW="146.65" CLOSE="148.97" VOLUME="39080070"/>
<row TRADEDATE="2014-07-02" OPEN="149.09" HIGH="151.95" LOW="148.9" CLOSE="151.95" VOLUME="48839500"/>
<row TRADEDATE="2014-07-03" OPEN="152" HIGH="153.66" LOW="151.41" CLOSE="152.3" VOLUME="48933580"/>
<row TRADEDATE="2014-07-04" OPEN="153" HIGH="153.09" LOW="148.25" CLOSE="149.13" VOLUME="38192290"/>
<row TRADEDATE="2014-07-07" OPEN="149.1" HIGH="151.4" LOW="149.09" CLOSE="150.31" VOLUME="34302070"/>
<row TRADEDATE="2014-07-08" OPEN="150.53" HIGH="153.53" LOW="150.52" CLOSE="151.43" VOLUME="50005770"/>
<row TRADEDATE="2014-07-09" OPEN="151.11" HIGH="151.77" LOW="149.01" CLOSE="150.4" VOLUME="44106880"/>
<row TRADEDATE="2014-07-10" OPEN="150.8" HIGH="151.52" LOW="147.1" CLOSE="148.79" VOLUME="58690960"/>
<row TRADEDATE="2014-07-11" OPEN="148.85" HIGH="149.25" LOW="146.91" CLOSE="148.15" VOLUME="36005010"/>
<row TRADEDATE="2014-07-14" OPEN="148.42" HIGH="148.8" LOW="146.51" CLOSE="147.5" VOLUME="38407230"/>
<row TRADEDATE="2014-07-15" OPEN="147.8" HIGH="148.37" LOW="146.52" CLOSE="146.52" VOLUME="55159950"/>
<row TRADEDATE="2014-07-16" OPEN="140.35" HIGH="143.1" LOW="140.1" CLOSE="142.5" VOLUME="55942320"/>
<row TRADEDATE="2014-07-17" OPEN="140.23" HIGH="141" LOW="138.23" CLOSE="140" VOLUME="61550720"/>
<row TRADEDATE="2014-07-18" OPEN="138" HIGH="139.41" LOW="136.5" CLOSE="139.26" VOLUME="53377680"/>
<row TRADEDATE="2014-07-21" OPEN="140.3" HIGH="140.44" LOW="135.2" CLOSE="136.01" VOLUME="46735750"/>
<row TRADEDATE="2014-07-22" OPEN="136.82" HIGH="138.87" LOW="136.05" CLOSE="137.75" VOLUME="35508000"/>
<row TRADEDATE="2014-07-23" OPEN="138.2" HIGH="139" LOW="135.2" CLOSE="136.29" VOLUME="35700000"/>
<row TRADEDATE="2014-07-24" OPEN="136" HIGH="137.36" LOW="135.15" CLOSE="136.9" VOLUME="23345280"/>
<row TRADEDATE="2014-07-25" OPEN="136.5" HIGH="136.83" LOW="134.22" CLOSE="135.12" VOLUME="35511270"/>
<row TRADEDATE="2014-07-28" OPEN="134.54" HIGH="134.73" LOW="130.9" CLOSE="132" VOLUME="44904250"/>
<row TRADEDATE="2014-07-29" OPEN="132.08" HIGH="133.73" LOW="130.55" CLOSE="131.31" VOLUME="36865680"/>
<row TRADEDATE="2014-07-30" OPEN="130.47" HIGH="135.41" LOW="130.1" CLOSE="133.4" VOLUME="42608490"/>
<row TRADEDATE="2014-07-31" OPEN="134.12" HIGH="135" LOW="131.21" CLOSE="132" VOLUME="41187230"/>
<row TRADEDATE="2014-08-01" OPEN="130.95" HIGH="131.99" LOW="130.21" CLOSE="131.5" VOLUME="31759700"/>
<row TRADEDATE="2014-08-04" OPEN="132" HIGH="132.79" LOW="128.25" CLOSE="129.5" VOLUME="44534400"/>
<row TRADEDATE="2014-08-05" OPEN="129.99" HIGH="130.1" LOW="126.28" CLOSE="126.57" VOLUME="46432510"/>
<row TRADEDATE="2014-08-06" OPEN="126.11" HIGH="126.5" LOW="123.23" CLOSE="124.7" VOLUME="68355310"/>
<row TRADEDATE="2014-08-07" OPEN="124.02" HIGH="128.77" LOW="122.79" CLOSE="126.92" VOLUME="64225030"/>
<row TRADEDATE="2014-08-08" OPEN="126.48" HIGH="129.37" LOW="126.33" CLOSE="126.55" VOLUME="56280080"/>
<row TRADEDATE="2014-08-11" OPEN="128.01" HIGH="130.45" LOW="127.84" CLOSE="128.3" VOLUME="43145400"/>
<row TRADEDATE="2014-08-12" OPEN="128.95" HIGH="129.95" LOW="127.24" CLOSE="128" VOLUME="38147150"/>
<row TRADEDATE="2014-08-13" OPEN="127.8" HIGH="131.84" LOW="127.7" CLOSE="131" VOLUME="57387480"/>
<row TRADEDATE="2014-08-14" OPEN="131.2" HIGH="132.49" LOW="130.34" CLOSE="131.41" VOLUME="43412620"/>
<row TRADEDATE="2014-08-15" OPEN="131.02" HIGH="133.47" LOW="130.62" CLOSE="132.67" VOLUME="42674890"/>
<row TRADEDATE="2014-08-18" OPEN="132.82" HIGH="134.4" LOW="132.11" CLOSE="134.29" VOLUME="28598600"/>
<row TRADEDATE="2014-08-19" OPEN="134.29" HIGH="136.4" LOW="134.28" CLOSE="136.2" VOLUME="38645630"/>
<row TRADEDATE="2014-08-20" OPEN="136.2" HIGH="136.8" LOW="135.16" CLOSE="136.7" VOLUME="22419120"/>
<row TRADEDATE="2014-08-21" OPEN="136.51" HIGH="137.69" LOW="135.55" CLOSE="136.49" VOLUME="34863190"/>
<row TRADEDATE="2014-08-22" OPEN="136.56" HIGH="137.2" LOW="134" CLOSE="135" VOLUME="38272800"/>
<row TRADEDATE="2014-08-25" OPEN="135.06" HIGH="136.46" LOW="135" CLOSE="136.09" VOLUME="16639450"/>
<row TRADEDATE="2014-08-26" OPEN="136.19" HIGH="136.99" LOW="134.71" CLOSE="135" VOLUME="27154630"/>
<row TRADEDATE="2014-08-27" OPEN="135.9" HIGH="136.67" LOW="135.12" CLOSE="135.51" VOLUME="24990540"/>
<row TRADEDATE="2014-08-28" OPEN="135.51" HIGH="135.74" LOW="131.94" CLOSE="133.8" VOLUME="47627370"/>
<row TRADEDATE="2014-08-29" OPEN="133.5" HIGH="134.17" LOW="131.81" CLOSE="131.95" VOLUME="35728900"/>
<row TRADEDATE="2014-09-01" OPEN="132.71" HIGH="134.75" LOW="131" CLOSE="132.32" VOLUME="41613580"/>
<row TRADEDATE="2014-09-02" OPEN="132.68" HIGH="133.32" LOW="131.34" CLOSE="133.32" VOLUME="25543730"/>
<row TRADEDATE="2014-09-03" OPEN="133.42" HIGH="139.63" LOW="133.33" CLOSE="138.26" VOLUME="64491970"/>
<row TRADEDATE="2014-09-04" OPEN="138.3" HIGH="139.29" LOW="136.8" CLOSE="138.15" VOLUME="43311610"/>
<row TRADEDATE="2014-09-05" OPEN="137.28" HIGH="140.13" LOW="136.36" CLOSE="139" VOLUME="37267050"/>
<row TRADEDATE="2014-09-08" OPEN="138.79" HIGH="139.38" LOW="136.87" CLOSE="139" VOLUME="31454520"/>
<row TRADEDATE="2014-09-09" OPEN="139.29" HIGH="140.82" LOW="138.86" CLOSE="139.02" VOLUME="26611960"/>
<row TRADEDATE="2014-09-10" OPEN="138.39" HIGH="139.4" LOW="137.62" CLOSE="139.2" VOLUME="20441450"/>
<row TRADEDATE="2014-09-11" OPEN="139.69" HIGH="140.28" LOW="136.51" CLOSE="136.65" VOLUME="34559170"/>
<row TRADEDATE="2014-09-12" OPEN="136.5" HIGH="138.56" LOW="136" CLOSE="137.56" VOLUME="34988310"/>
<row TRADEDATE="2014-09-15" OPEN="137.26" HIGH="138.12" LOW="135.35" CLOSE="136" VOLUME="40717130"/>
<row TRADEDATE="2014-09-16" OPEN="136.01" HIGH="139.58" LOW="135.26" CLOSE="138.56" VOLUME="40431640"/>
<row TRADEDATE="2014-09-17" OPEN="138.5" HIGH="139.34" LOW="136.05" CLOSE="137" VOLUME="39757700"/>
<row TRADEDATE="2014-09-18" OPEN="137.25" HIGH="138.4" LOW="136.51" CLOSE="138.2" VOLUME="29247410"/>
<row TRADEDATE="2014-09-19" OPEN="138" HIGH="138" LOW="134.48" CLOSE="135.99" VOLUME="45103990"/>
<row TRADEDATE="2014-09-22" OPEN="135.76" HIGH="136.83" LOW="134.6" CLOSE="135.05" VOLUME="27258240"/>
<row TRADEDATE="2014-09-23" OPEN="135.55" HIGH="137.2" LOW="135.47" CLOSE="136.5" VOLUME="29141830"/>
<row TRADEDATE="2014-09-24" OPEN="136.99" HIGH="138.65" LOW="136.88" CLOSE="137.8" VOLUME="32271690"/>
<row TRADEDATE="2014-09-25" OPEN="138.28" HIGH="138.96" LOW="136.52" CLOSE="136.92" VOLUME="31511120"/>
<row TRADEDATE="2014-09-26" OPEN="136.51" HIGH="137.95" LOW="135.71" CLOSE="137.11" VOLUME="34925980"/>
<row TRADEDATE="2014-09-29" OPEN="138" HIGH="138.57" LOW="135" CLOSE="135.77" VOLUME="36985740"/>
<row TRADEDATE="2014-09-30" OPEN="136.27" HIGH="139.13" LOW="135.14" CLOSE="137.9" VOLUME="50261030"/>
<row TRADEDATE="2014-10-01" OPEN="137.5" HIGH="139.86" LOW="137.12" CLOSE="137.26" VOLUME="37398300"/>
<row TRADEDATE="2014-10-02" OPEN="136.8" HIGH="137.44" LOW="133.7" CLOSE="134.25" VOLUME="42243810"/>
<row TRADEDATE="2014-10-03" OPEN="134.97" HIGH="138.07" LOW="134.87" CLOSE="135.8" VOLUME="32174540"/>
<row TRADEDATE="2014-10-06" OPEN="136.61" HIGH="139.63" LOW="136.61" CLOSE="138.9" VOLUME="41322460"/>
<row TRADEDATE="2014-10-07" OPEN="139.01" HIGH="139.5" LOW="136.8" CLOSE="137.1" VOLUME="28875580"/>
<row TRADEDATE="2014-10-08" OPEN="136.19" HIGH="137" LOW="134.61" CLOSE="134.61" VOLUME="34466460"/>
<row TRADEDATE="2014-10-09" OPEN="136.2" HIGH="137.26" LOW="134.55" CLOSE="135.64" VOLUME="37768210"/>
<row TRADEDATE="2014-10-10" OPEN="134.3" HIGH="134.6" LOW="132.09" CLOSE="133.21" VOLUME="42598080"/>
<row TRADEDATE="2014-10-13" OPEN="133" HIGH="136.4" LOW="132.32" CLOSE="135.25" VOLUME="30923230"/>
<row TRADEDATE="2014-10-14" OPEN="135.3" HIGH="136.92" LOW="134.51" CLOSE="135.5" VOLUME="35709120"/>
<row TRADEDATE="2014-10-15" OPEN="134.9" HIGH="136.48" LOW="134.25" CLOSE="134.5" VOLUME="32324170"/>
<row TRADEDATE="2014-10-16" OPEN="135" HIGH="135.59" LOW="131.93" CLOSE="132.41" VOLUME="47983260"/>
<row TRADEDATE="2014-10-17" OPEN="133.5" HIGH="135.4" LOW="133.01" CLOSE="134.6" VOLUME="30074200"/>
<row TRADEDATE="2014-10-20" OPEN="135.2" HIGH="136.18" LOW="133.14" CLOSE="134.1" VOLUME="32118700"/>
<row TRADEDATE="2014-10-21" OPEN="134" HIGH="134.95" LOW="132.94" CLOSE="134" VOLUME="24848020"/>
<row TRADEDATE="2014-10-22" OPEN="134.51" HIGH="134.66" LOW="132.25" CLOSE="133.5" VOLUME="32439110"/>
<row TRADEDATE="2014-10-23" OPEN="132.51" HIGH="134.15" LOW="131.42" CLOSE="133.5" VOLUME="36223010"/>
<row TRADEDATE="2014-10-24" OPEN="133.5" HIGH="134.3" LOW="132.35" CLOSE="133.99" VOLUME="24372990"/>
<row TRADEDATE="2014-10-27" OPEN="135" HIGH="136.05" LOW="133.5" CLOSE="134.07" VOLUME="31605210"/>
<row TRADEDATE="2014-10-28" OPEN="134.62" HIGH="136.14" LOW="134.1" CLOSE="135.75" VOLUME="27903910"/>
</rows>
</data>
</document>